{
  "held_out_participant_ids": [
    14,
    16,
    20,
    27,
    33,
    44,
    45,
    47
  ],
  "split_design": {
    "method": "stratified_by_cycle_count_seed42",
    "n_held_out": 8,
    "n_total_2022": 42,
    "held_out_pct": 19.0,
    "strata": {
      "2_cycle": [
        16
      ],
      "3_cycle": [
        14,
        27,
        33,
        45,
        47
      ],
      "4_cycle": [
        20,
        44
      ]
    },
    "pid_49_excluded_from_pool": "only 38 rows (short study entry)",
    "pid_50_excluded_from_pool": "sole 5-cycle participant \u2014 too rare to hold out",
    "note": "These participants must not appear in any training or CV fold. They are reserved for a single final comparison between model versions. Do not reshuffle this split after any model has been evaluated against it."
  }
}